kahi_impactu_postcalculations/Kahi_impactu_postcalculations.py
kahi_impactu_postcalculations/__init__.py
kahi_impactu_postcalculations/_version.py
kahi_impactu_postcalculations/denormalization.py
kahi_impactu_postcalculations/indexes.py
kahi_impactu_postcalculations/process_one.py
Kahi_impactu_postcalculations-0.1.3.dist-info/LICENSE
Kahi_impactu_postcalculations-0.1.3.dist-info/METADATA
Kahi_impactu_postcalculations-0.1.3.dist-info/WHEEL
Kahi_impactu_postcalculations-0.1.3.dist-info/top_level.txt
Kahi_impactu_postcalculations-0.1.3.dist-info/RECORD
