Metadata-Version: 2.2
Name: Kahi_impactu_postcalculations
Version: 0.1.3
Summary: Kahi plugin post processing calculations for impactu
Home-page: https://github.com/colav/Kahi_plugins
Author: Colav
Author-email: colav@udea.edu.co
License: BSD
License-File: LICENSE
Requires-Dist: kahi
Requires-Dist: pymongo
Requires-Dist: spacy
Requires-Dist: joblib
Requires-Dist: datetime
Dynamic: author
Dynamic: author-email
Dynamic: description
Dynamic: description-content-type
Dynamic: home-page
Dynamic: license
Dynamic: requires-dist
Dynamic: summary
